src/oraculum-service/__init__.py
src/oraculum-service/version.py
src/oraculum-service/core/__init__.py
src/oraculum-service/utils/__init__.py
oraculum_service-0.0.1.dist-info/METADATA
oraculum_service-0.0.1.dist-info/WHEEL
oraculum_service-0.0.1.dist-info/licenses/LICENSE
oraculum_service-0.0.1.dist-info/RECORD
